whiterock/__init__.py
whiterock/agents.py
whiterock/prompts.py
whiterock-0.0.1.dist-info/LICENSE
whiterock-0.0.1.dist-info/METADATA
whiterock-0.0.1.dist-info/WHEEL
whiterock-0.0.1.dist-info/RECORD
